pyigt/__init__.py
pyigt/__main__.py
pyigt/cli_util.py
pyigt/igt.py
pyigt/index.html
pyigt/lgrmorphemes.py
pyigt/util.py
pyigt/commands/__init__.py
pyigt/commands/ls.py
pyigt/commands/stats.py
pyigt-2.2.0.dist-info/LICENSE
pyigt-2.2.0.dist-info/METADATA
pyigt-2.2.0.dist-info/WHEEL
pyigt-2.2.0.dist-info/entry_points.txt
pyigt-2.2.0.dist-info/top_level.txt
pyigt-2.2.0.dist-info/RECORD
