Metadata-Version: 2.1
Name: pyigt
Version: 2.2.0
Summary: A Python library for handling inter-linear-glossed text.
Home-page: https://github.com/cldf/pyigt
Author: Johann-Mattis List and Robert Forkel
Author-email: robert_forkel@eva.mpg.de
License: GPL
Project-URL: Bug Tracker, https://github.com/cldf/pyigt/issues
Keywords: Chinese linguistics,historical linguistics,computer-assisted language comparison
Platform: any
Classifier: Development Status :: 5 - Production/Stable
Classifier: Intended Audience :: Developers
Classifier: Intended Audience :: Science/Research
Classifier: Natural Language :: English
Classifier: Operating System :: OS Independent
Classifier: Programming Language :: Python :: 3
Classifier: Programming Language :: Python :: 3.9
Classifier: Programming Language :: Python :: 3.10
Classifier: Programming Language :: Python :: 3.11
Classifier: Programming Language :: Python :: 3.12
Classifier: Programming Language :: Python :: 3.13
Classifier: Programming Language :: Python :: Implementation :: CPython
Classifier: Programming Language :: Python :: Implementation :: PyPy
Requires-Python: >=3.8
License-File: LICENSE
Requires-Dist: attrs
Requires-Dist: csvw
Requires-Dist: clldutils
Requires-Dist: pycldf
Requires-Dist: segments>=2.0.0
Requires-Dist: tabulate
Provides-Extra: dev
Requires-Dist: flake8; extra == "dev"
Requires-Dist: wheel; extra == "dev"
Requires-Dist: twine; extra == "dev"
Requires-Dist: build; extra == "dev"
Provides-Extra: docs
Requires-Dist: sphinx<7; extra == "docs"
Requires-Dist: sphinx-autodoc-typehints; extra == "docs"
Requires-Dist: sphinx-rtd-theme; extra == "docs"
Provides-Extra: lingpy
Requires-Dist: lingpy>=2.6.5; extra == "lingpy"
Provides-Extra: test
Requires-Dist: pytest; extra == "test"
Requires-Dist: pytest-mock; extra == "test"
Requires-Dist: pytest-cov; extra == "test"
Requires-Dist: coverage>=4.2; extra == "test"
Requires-Dist: lingpy>=2.6.5; extra == "test"
